<?xml version="1.0" encoding="utf-8"?>
<TextureAtlas imagePath="NOTE_splash.png">
	<!-- Created with Adobe Animate version 21.0.6.41649 -->
	<!-- http://www.adobe.com/products/animate.html -->
	<SubTexture name="note impact 1 blue0000" x="10" y="860" width="189" height="270" frameX="-32" frameY="-12" frameWidth="260" frameHeight="298"/>
	<SubTexture name="note impact 1 blue0001" x="10" y="585" width="213" height="265" frameX="-27" frameY="-22" frameWidth="260" frameHeight="298"/>
	<SubTexture name="note impact 1 blue0002" x="1090" y="10" width="252" height="291" frameX="-4" frameY="-6" frameWidth="260" frameHeight="298"/>
	<SubTexture name="note impact 1 blue0003" x="10" y="10" width="260" height="298"/>
	<SubTexture name="note impact 1 green0000" x="209" y="860" width="189" height="270" frameX="-32" frameY="-12" frameWidth="260" frameHeight="298"/>
	<SubTexture name="note impact 1 green0001" x="233" y="585" width="213" height="265" frameX="-27" frameY="-22" frameWidth="260" frameHeight="298"/>
	<SubTexture name="note impact 1 green0002" x="1352" y="10" width="252" height="291" frameX="-4" frameY="-6" frameWidth="260" frameHeight="298"/>
	<SubTexture name="note impact 1 green0003" x="280" y="10" width="260" height="298"/>
	<SubTexture name="note impact 1 purple0000" x="902" y="860" width="189" height="270" frameX="-32" frameY="-12" frameWidth="260" frameHeight="298"/>
	<SubTexture name="note impact 1 purple0001" x="456" y="586" width="213" height="265" frameX="-27" frameY="-22" frameWidth="260" frameHeight="298"/>
	<SubTexture name="note impact 1 purple0002" x="1614" y="10" width="252" height="291" frameX="-4" frameY="-6" frameWidth="260" frameHeight="298"/>
	<SubTexture name="note impact 1 purple0003" x="550" y="10" width="260" height="298"/>
	<SubTexture name="note impact 1 red0000" x="408" y="861" width="189" height="270" frameX="-32" frameY="-12" frameWidth="260" frameHeight="298"/>
	<SubTexture name="note impact 1 red0001" x="679" y="586" width="213" height="265" frameX="-27" frameY="-22" frameWidth="260" frameHeight="298"/>
	<SubTexture name="note impact 1 red0002" x="1090" y="311" width="252" height="291" frameX="-4" frameY="-6" frameWidth="260" frameHeight="298"/>
	<SubTexture name="note impact 1 red0003" x="820" y="10" width="260" height="298"/>
	<SubTexture name="note impact 2 blue0000" x="1820" y="578" width="169" height="201" frameX="-45" frameY="-41" frameWidth="274" frameHeight="267"/>
	<SubTexture name="note impact 2 blue0001" x="902" y="612" width="225" height="238" frameX="-20" frameY="-19" frameWidth="274" frameHeight="267"/>
	<SubTexture name="note impact 2 blue0002" x="1352" y="311" width="265" height="257" frameX="0" frameY="-10" frameWidth="274" frameHeight="267"/>
	<SubTexture name="note impact 2 blue0003" x="560" y="318" width="224" height="258" frameX="-50" frameY="0" frameWidth="274" frameHeight="267"/>
	<SubTexture name="note impact 2 green0000" x="1137" y="612" width="169" height="201" frameX="-45" frameY="-41" frameWidth="274" frameHeight="267"/>
	<SubTexture name="note impact 2 green0001" x="1137" y="846" width="225" height="238" frameX="-20" frameY="-19" frameWidth="274" frameHeight="267"/>
	<SubTexture name="note impact 2 green0002" x="1627" y="311" width="265" height="257" frameX="0" frameY="-10" frameWidth="274" frameHeight="267"/>
	<SubTexture name="note impact 2 green0003" x="794" y="318" width="224" height="258" frameX="-50" frameY="0" frameWidth="274" frameHeight="267"/>
	<SubTexture name="note impact 2 purple0000" x="1842" y="789" width="169" height="201" frameX="-45" frameY="-41" frameWidth="274" frameHeight="267"/>
	<SubTexture name="note impact 2 purple0001" x="1372" y="846" width="225" height="238" frameX="-20" frameY="-19" frameWidth="274" frameHeight="267"/>
	<SubTexture name="note impact 2 purple0002" x="10" y="318" width="265" height="257" frameX="0" frameY="-10" frameWidth="274" frameHeight="267"/>
	<SubTexture name="note impact 2 purple0003" x="1352" y="578" width="224" height="258" frameX="-50" frameY="0" frameWidth="274" frameHeight="267"/>
	<SubTexture name="note impact 2 red0000" x="607" y="861" width="169" height="201" frameX="-45" frameY="-41" frameWidth="274" frameHeight="267"/>
	<SubTexture name="note impact 2 red0001" x="1607" y="846" width="225" height="238" frameX="-20" frameY="-19" frameWidth="274" frameHeight="267"/>
	<SubTexture name="note impact 2 red0002" x="285" y="318" width="265" height="257" frameX="0" frameY="-10" frameWidth="274" frameHeight="267"/>
	<SubTexture name="note impact 2 red0003" x="1586" y="578" width="224" height="258" frameX="-50" frameY="0" frameWidth="274" frameHeight="267"/>
</TextureAtlas>
