{"song":{"player2":"dad","player1":"bf","notes":[{"sectionNotes":[[0,2,0,""],[600,3,600,""],[1200,3,600,""]],"altAnim":false,"changeBPM":false,"bpm":0,"lengthInSteps":16,"mustHitSection":false},{"sectionNotes":[[2400,6,0,""],[3000,7,600,""],[3600,7,600,""]],"altAnim":false,"changeBPM":false,"bpm":0,"lengthInSteps":16,"mustHitSection":false},{"sectionNotes":[[4800,1,300,""],[5400,0,300,""],[6000,3,600,""]],"altAnim":false,"changeBPM":false,"bpm":0,"lengthInSteps":16,"mustHitSection":false},{"sectionNotes":[[7200,5,300,""],[7800,4,300,""],[8400,7,600,""]],"altAnim":false,"changeBPM":false,"bpm":0,"lengthInSteps":16,"mustHitSection":false},{"sectionNotes":[[9600,1,300,""],[10200,3,0,""],[10500,0,0,""],[10800,1,600,""]],"altAnim":false,"changeBPM":false,"bpm":0,"lengthInSteps":16,"mustHitSection":false},{"sectionNotes":[[12000,5,300,""],[12600,7,0,""],[12900,4,0,""],[13200,5,600,""]],"altAnim":false,"changeBPM":false,"bpm":0,"lengthInSteps":16,"mustHitSection":false},{"sectionNotes":[[14400,3,0,""],[14700,1,0,""],[15300,0,0,""],[15600,2,600,""]],"altAnim":false,"changeBPM":false,"bpm":0,"lengthInSteps":16,"mustHitSection":false},{"sectionNotes":[[16800,7,0,""],[17100,5,0,""],[17700,4,0,""],[18000,6,600,""]],"altAnim":false,"changeBPM":false,"bpm":0,"lengthInSteps":16,"mustHitSection":false},{"sectionNotes":[[19200,0,0,""],[19500,3,0,""],[19800,1,900,""]],"altAnim":false,"changeBPM":false,"bpm":0,"lengthInSteps":16,"mustHitSection":false},{"sectionNotes":[[21600,4,0,""],[21900,7,0,""],[22200,5,900,""]],"altAnim":false,"changeBPM":false,"bpm":0,"lengthInSteps":16,"mustHitSection":false},{"sectionNotes":[[24000,1,0,""],[24300,3,0,""],[24600,0,900,""]],"altAnim":false,"changeBPM":false,"bpm":0,"lengthInSteps":16,"mustHitSection":false},{"sectionNotes":[[26400,5,0,""],[26700,7,0,""],[27000,4,900,""]],"altAnim":false,"changeBPM":false,"bpm":0,"lengthInSteps":16,"mustHitSection":false},{"sectionNotes":[[28800,2,0,""],[29100,3,0,""],[29400,0,1200,""]],"altAnim":false,"changeBPM":false,"bpm":0,"lengthInSteps":16,"mustHitSection":false},{"sectionNotes":[[31200,6,0,""],[31500,7,0,""],[31800,4,1200,""],[33300,2,0,""]],"altAnim":false,"changeBPM":false,"bpm":0,"lengthInSteps":16,"mustHitSection":false},{"sectionNotes":[[33600,0,0,""],[33900,3,0,""],[34500,2,0,""],[34575,0,0,""],[34800,1,600,""],[35700,6,0,""]],"altAnim":false,"changeBPM":false,"bpm":0,"lengthInSteps":16,"mustHitSection":false},{"sectionNotes":[[36000,4,0,""],[36300,7,0,""],[36900,6,0,""],[36975,4,0,""],[37200,5,600,""]],"altAnim":false,"changeBPM":false,"bpm":0,"lengthInSteps":16,"mustHitSection":false},{"sectionNotes":[[38400,2,450,""],[39000,3,300,""],[39600,0,600,""]],"altAnim":false,"changeBPM":false,"bpm":0,"lengthInSteps":16,"mustHitSection":false},{"sectionNotes":[[40800,6,450,""],[41400,7,300,""],[42000,4,600,""]],"altAnim":false,"changeBPM":false,"bpm":0,"lengthInSteps":16,"mustHitSection":false},{"sectionNotes":[[43200,1,0,""],[43800,2,0,""],[44400,1,0,""],[44550,1,0,""],[44700,1,0,""],[45000,2,0,""]],"altAnim":false,"changeBPM":false,"bpm":0,"lengthInSteps":16,"mustHitSection":false},{"sectionNotes":[[45600,5,0,""],[46200,6,0,""],[46800,5,0,""],[46950,5,0,""],[47100,5,0,""],[47400,6,0,""]],"altAnim":false,"changeBPM":false,"bpm":0,"lengthInSteps":16,"mustHitSection":false},{"sectionNotes":[[48000,2,450,""],[48600,3,300,""],[49200,0,450,""]],"altAnim":false,"changeBPM":false,"bpm":0,"lengthInSteps":16,"mustHitSection":false},{"sectionNotes":[[50400,6,450,""],[51000,7,300,""],[51600,4,450,""]],"altAnim":false,"changeBPM":false,"bpm":0,"lengthInSteps":16,"mustHitSection":false},{"sectionNotes":[[52800,3,1800,""]],"altAnim":false,"changeBPM":false,"bpm":0,"lengthInSteps":16,"mustHitSection":false},{"sectionNotes":[[55200,7,1800,""]],"altAnim":false,"changeBPM":false,"bpm":0,"lengthInSteps":16,"mustHitSection":false},{"sectionNotes":[[57600,2,0,""],[57900,3,0,""],[58200,0,1200,""]],"altAnim":false,"changeBPM":false,"bpm":0,"lengthInSteps":16,"mustHitSection":false},{"sectionNotes":[[60000,6,0,""],[60300,7,0,""],[60600,4,1200,""],[62100,2,0,""]],"altAnim":false,"changeBPM":false,"bpm":0,"lengthInSteps":16,"mustHitSection":false},{"sectionNotes":[[62400,0,0,""],[62700,3,0,""],[63300,2,0,""],[63375,0,0,""],[63600,1,600,""],[64500,6,0,""]],"altAnim":false,"changeBPM":false,"bpm":0,"lengthInSteps":16,"mustHitSection":false},{"sectionNotes":[[64800,4,0,""],[65100,7,0,""],[65700,6,0,""],[65775,4,0,""],[66000,5,600,""]],"altAnim":false,"changeBPM":false,"bpm":0,"lengthInSteps":16,"mustHitSection":false},{"sectionNotes":[[67200,2,0,""],[67500,3,0,""],[67800,0,0,""],[68100,2,0,""],[68400,1,600,""]],"altAnim":false,"changeBPM":false,"bpm":0,"lengthInSteps":16,"mustHitSection":false},{"sectionNotes":[[69600,6,0,""],[69900,7,0,""],[70200,4,0,""],[70500,6,0,""],[70800,5,600,""],[71700,2,0,""]],"altAnim":false,"changeBPM":false,"bpm":0,"lengthInSteps":16,"mustHitSection":false},{"sectionNotes":[[72000,0,0,""],[72300,3,0,""],[72900,2,0,""],[72975,0,0,""],[73200,1,600,""],[74100,6,0,""]],"altAnim":false,"changeBPM":false,"bpm":0,"lengthInSteps":16,"mustHitSection":false},{"sectionNotes":[[74400,4,0,""],[74700,7,0,""],[75300,6,0,""],[75375,4,0,""],[75600,5,600,""]],"altAnim":false,"changeBPM":false,"bpm":0,"lengthInSteps":16,"mustHitSection":false}],"validScore":true,"needsVoices":true,"song":"Bopeebo","bpm":100,"speed":1.3}}